LICENSE.txt
README.md
setup.py
caafg/__init__.py
caafg.egg-info/PKG-INFO
caafg.egg-info/SOURCES.txt
caafg.egg-info/dependency_links.txt
caafg.egg-info/requires.txt
caafg.egg-info/top_level.txt
caafg/dataset/__init__.py
caafg/dataset/dataset.py
caafg/generators/__init__.py
caafg/generators/blueprintcaafg/__init__.py
caafg/generators/blueprintcaafg/consts.py
caafg/generators/blueprintcaafg/core.py
caafg/generators/blueprintcaafg/generator.py
caafg/generators/blueprintcaafg/operators.py
caafg/interfaces/__init__.py
caafg/interfaces/interfaces.py
caafg/models/__init__.py