Metadata-Version: 2.1
Name: caafg
Version: 0.0.3
Summary: Context Aware Automated Feature Generators with LLMs
Home-page: https://github.com/jariskueken/caafg/
Author: Jaris Küken
Author-email: jaris.kueken@gmail.com
License: LICENSE.txt
Classifier: Development Status :: 2 - Pre-Alpha
Classifier: Programming Language :: Python :: 3
Classifier: Operating System :: OS Independent
Requires-Python: >=3.10
License-File: LICENSE.txt
Requires-Dist: remoteinference
